setup.py
python_twitpic.egg-info/PKG-INFO
python_twitpic.egg-info/SOURCES.txt
python_twitpic.egg-info/dependency_links.txt
python_twitpic.egg-info/requires.txt
python_twitpic.egg-info/top_level.txt
script/twitpic
twitpic/__init__.py
twitpic/twitpic2.py