Metadata-Version: 1.0
Name: python-twitpic
Version: 2.1
Summary: Python TwitPic Client API
Home-page: https://github.com/macmichael01/python-twitpic
Author: Chris McMichael
Author-email: macmichael01@gmail.com
License: BSD
Keywords: twitpic photos tweets
Platform: UNKNOWN
